Metadata-Version: 1.0
Name: tbs2022-distributions
Version: 0.1
Summary: TBS Gaussian and Binomial distributions
Home-page: UNKNOWN
Author: UNKNOWN
Author-email: UNKNOWN
License: UNKNOWN
Platform: UNKNOWN
